<?xml version="1.0" encoding="iso-8859-1" standalone="yes" ?>

<!-- 
    A sample installation file.
    Use it as a base for your own installers :-)
    
    To compile it :
    - go in the bin directory where you installed IzPack
    - call "compile ../sample/install.xml -b ../sample"
-->

<installation version="1.0">

    <!-- 
        The info section.
        The meaning of the tags should be natural ...
    -->
    <info>
        <appname>MultiBit</appname>
        <appsubpath>MultiBit-${project.version}</appsubpath>
        <appversion>${project.version}</appversion>
        <url>https://multibit.org/</url>
        <uninstaller write="yes" />
        <javaversion>1.6</javaversion>
    </info>

<variables>
  <variable name="ShowCreateDirectoryMessage" value="false"/>
  <variable name="DesktopShortcutCheckboxEnabled" value="true"/>
</variables>

    <!-- 
        The gui preferences indication.
        Sets the installer window to 640x480. It will not be able to change the size.
    -->
    <guiprefs width="640" height="480" resizable="yes"/>

    <!-- 
        The locale section.
        Asks here to include the English langpacks.
    -->
    <locale>
        <langpack iso3="eng"/>
    </locale>

    <!-- 
        The resources section.
        The ids must be these ones if you want to use the LicencePanel and/or the InfoPanel.
    -->
    <resources>
        <res id="LicencePanel.licence" src="COPYING"/>
        <res id="InfoPanel.info" src="readme.txt"/>
        <res id="Installer.image" src="installerLeft.png" />
        <res id="shortcutSpec.xml" src="Unix_shortcutSpec.xml"/>
    </resources>

    <!-- 
        The panels section.
        We indicate here which panels we want to use. The order will be respected.
    -->
    <panels>
        <panel classname="HelloPanel"/>
        <panel classname="InfoPanel"/>
        <panel classname="LicencePanel"/>
        <panel classname="TargetPanel"/>
        <panel classname="ShortcutPanel"/>
        <panel classname="InstallPanel"/>
        <panel classname="FinishPanel"/>
    </panels>

    <!-- 
        The packs section.
        We specify here our packs.
    -->
    <packs>
        <pack name="MultiBit" required="yes">
            <description>MultiBit install files.</description>
            <file src="readme.txt" targetdir="$INSTALL_PATH"/>
            <file src="configuration.md" targetdir="$INSTALL_PATH"/>
            <file src="multibit48.png" targetdir="$INSTALL_PATH"/>
            <file src="multibit.checkpoints" targetdir="$INSTALL_PATH"/>
            <file src="release_notes.txt" targetdir="$INSTALL_PATH"/>
            <file src="COPYING" targetdir="$INSTALL_PATH"/>
            <file src="authors.txt" targetdir="$INSTALL_PATH"/>
            <file src="multibit-exe.jar" targetdir="$INSTALL_PATH"/>
            <file src="multibit-protocol-handler.sh" targetdir="$INSTALL_PATH" os="linux"/>
            <parsable targetfile="$INSTALL_PATH/multibit-protocol-handler.sh"  os="linux"/>
            <executable type="bin" stage="never" targetfile="$INSTALL_PATH/multibit-protocol-handler.sh" os="linux" />
            <executable type="bin" stage="postinstall" targetfile="$INSTALL_PATH/multibit-protocol-handler.sh" os="linux" />
        </pack>
    </packs>
</installation>
